markdrip/__init__.py
markdrip/css/github.css
markdrip/main.py
markdrip/mods/generator.py
markdrip/templete/base.html
markdrip-0.1.4.dist-info/entry_points.txt
markdrip-0.1.4.dist-info/LICENSE
markdrip-0.1.4.dist-info/WHEEL
markdrip-0.1.4.dist-info/METADATA
markdrip-0.1.4.dist-info/RECORD
