Metadata-Version: 2.1
Name: markdrip
Version: 0.1.4
Summary: Simple MarkDown renderer
Home-page: https://github.com/Comamoca/MarkDrip
Author: Comamoca
Author-email: comamoca.dev@gmail.com
Requires-Python: >=3.10,<4.0
Classifier: Programming Language :: Python :: 3
Classifier: Programming Language :: Python :: 3.10
Requires-Dist: Jinja2 (>=3.1.1,<4.0.0)
Requires-Dist: click (>=8.0.4,<9.0.0)
Requires-Dist: mistletoe (>=0.8.2,<0.9.0)
Project-URL: Repository, https://github.com/Comamoca/MarkDrip
